{"timeline": {"headline": "Test", "text": "Haha！", "type": "default", "date": [{"headline": "BEB001", "startDate": 1, "endDate": 1, "asset": {"media": "http://pics.dmm.co.jp/digital/video/beb00001/beb00001pl.jpg"}, "text": "for Fun"}, {"headline": "BEB002", "startDate": 2, "endDate": 2, "asset": {"media": "http://pics.dmm.co.jp/digital/video/beb00002/beb00002pl.jpg"}, "text": "for Fun"}, {"headline": "BEB003", "startDate": 3, "endDate": 3, "asset": {"media": "http://pics.dmm.co.jp/digital/video/beb00003/beb00003pl.jpg"}, "text": "for Fun"}, {"headline": "BEB004", "startDate": 4, "endDate": 4, "asset": {"media": "http://pics.dmm.co.jp/digital/video/beb00004/beb00004pl.jpg"}, "text": "for Fun"}, {"headline": "BEB005", "startDate": 5, "endDate": 5, "asset": {"media": "http://pics.dmm.co.jp/digital/video/beb00005/beb00005pl.jpg"}, "text": "for Fun"}, {"headline": "BEB006", "startDate": 6, "endDate": 6, "asset": {"media": "http://pics.dmm.co.jp/digital/video/beb00006/beb00006pl.jpg"}, "text": "for Fun"}, {"headline": "BEB007", "startDate": 7, "endDate": 7, "asset": {"media": "http://pics.dmm.co.jp/digital/video/beb00007/beb00007pl.jpg"}, "text": "for Fun"}, {"headline": "BEB008", "startDate": 8, "endDate": 8, "asset": {"media": "http://pics.dmm.co.jp/digital/video/beb00008/beb00008pl.jpg"}, "text": "for Fun"}, {"headline": "BEB009", "startDate": 9, "endDate": 9, "asset": {"media": "http://pics.dmm.co.jp/digital/video/beb00009/beb00009pl.jpg"}, "text": "for Fun"}, {"headline": "BEB010", "startDate": 10, "endDate": 10, "asset": {"media": "http://pics.dmm.co.jp/digital/video/beb00010/beb00010pl.jpg"}, "text": "for Fun"}, {"headline": "BEB011", "startDate": 11, "endDate": 11, "asset": {"media": "http://pics.dmm.co.jp/digital/video/beb00011/beb00011pl.jpg"}, "text": "for Fun"}, {"headline": "BEB012", "startDate": 12, "endDate": 12, "asset": {"media": "http://pics.dmm.co.jp/digital/video/beb00012/beb00012pl.jpg"}, "text": "for Fun"}, {"headline": "BEB013", "startDate": 13, "endDate": 13, "asset": {"media": "http://pics.dmm.co.jp/digital/video/beb00013/beb00013pl.jpg"}, "text": "for Fun"}, {"headline": "BEB014", "startDate": 14, "endDate": 14, "asset": {"media": "http://pics.dmm.co.jp/digital/video/beb00014/beb00014pl.jpg"}, "text": "for Fun"}, {"headline": "BEB015", "startDate": 15, "endDate": 15, "asset": {"media": "http://pics.dmm.co.jp/digital/video/beb00015/beb00015pl.jpg"}, "text": "for Fun"}, {"headline": "BEB016", "startDate": 16, "endDate": 16, "asset": {"media": "http://pics.dmm.co.jp/digital/video/beb00016/beb00016pl.jpg"}, "text": "for Fun"}, {"headline": "BEB017", "startDate": 17, "endDate": 17, "asset": {"media": "http://pics.dmm.co.jp/digital/video/beb00017/beb00017pl.jpg"}, "text": "for Fun"}, {"headline": "BEB018", "startDate": 18, "endDate": 18, "asset": {"media": "http://pics.dmm.co.jp/digital/video/beb00018/beb00018pl.jpg"}, "text": "for Fun"}, {"headline": "BEB019", "startDate": 19, "endDate": 19, "asset": {"media": "http://pics.dmm.co.jp/digital/video/beb00019/beb00019pl.jpg"}, "text": "for Fun"}, {"headline": "BEB020", "startDate": 20, "endDate": 20, "asset": {"media": "http://pics.dmm.co.jp/digital/video/beb00020/beb00020pl.jpg"}, "text": "for Fun"}, {"headline": "BEB021", "startDate": 21, "endDate": 21, "asset": {"media": "http://pics.dmm.co.jp/digital/video/beb00021/beb00021pl.jpg"}, "text": "for Fun"}, {"headline": "BEB022", "startDate": 22, "endDate": 22, "asset": {"media": "http://pics.dmm.co.jp/digital/video/beb00022/beb00022pl.jpg"}, "text": "for Fun"}, {"headline": "BEB023", "startDate": 23, "endDate": 23, "asset": {"media": "http://pics.dmm.co.jp/digital/video/beb00023/beb00023pl.jpg"}, "text": "for Fun"}, {"headline": "BEB024", "startDate": 24, "endDate": 24, "asset": {"media": "http://pics.dmm.co.jp/digital/video/beb00024/beb00024pl.jpg"}, "text": "for Fun"}, {"headline": "BEB025", "startDate": 25, "endDate": 25, "asset": {"media": "http://pics.dmm.co.jp/digital/video/beb00025/beb00025pl.jpg"}, "text": "for Fun"}, {"headline": "BEB026", "startDate": 26, "endDate": 26, "asset": {"media": "http://pics.dmm.co.jp/digital/video/beb00026/beb00026pl.jpg"}, "text": "for Fun"}, {"headline": "BEB027", "startDate": 27, "endDate": 27, "asset": {"media": "http://pics.dmm.co.jp/digital/video/beb00027/beb00027pl.jpg"}, "text": "for Fun"}, {"headline": "BEB028", "startDate": 28, "endDate": 28, "asset": {"media": "http://pics.dmm.co.jp/digital/video/beb00028/beb00028pl.jpg"}, "text": "for Fun"}, {"headline": "BEB029", "startDate": 29, "endDate": 29, "asset": {"media": "http://pics.dmm.co.jp/digital/video/beb00029/beb00029pl.jpg"}, "text": "for Fun"}, {"headline": "BEB030", "startDate": 30, "endDate": 30, "asset": {"media": "http://pics.dmm.co.jp/digital/video/beb00030/beb00030pl.jpg"}, "text": "for Fun"}, {"headline": "BEB031", "startDate": 31, "endDate": 31, "asset": {"media": "http://pics.dmm.co.jp/digital/video/beb00031/beb00031pl.jpg"}, "text": "for Fun"}, {"headline": "BEB032", "startDate": 32, "endDate": 32, "asset": {"media": "http://pics.dmm.co.jp/digital/video/beb00032/beb00032pl.jpg"}, "text": "for Fun"}, {"headline": "BEB033", "startDate": 33, "endDate": 33, "asset": {"media": "http://pics.dmm.co.jp/digital/video/beb00033/beb00033pl.jpg"}, "text": "for Fun"}, {"headline": "BEB034", "startDate": 34, "endDate": 34, "asset": {"media": "http://pics.dmm.co.jp/digital/video/beb00034/beb00034pl.jpg"}, "text": "for Fun"}, {"headline": "BEB035", "startDate": 35, "endDate": 35, "asset": {"media": "http://pics.dmm.co.jp/digital/video/beb00035/beb00035pl.jpg"}, "text": "for Fun"}, {"headline": "BEB036", "startDate": 36, "endDate": 36, "asset": {"media": "http://pics.dmm.co.jp/digital/video/beb00036/beb00036pl.jpg"}, "text": "for Fun"}, {"headline": "BEB037", "startDate": 37, "endDate": 37, "asset": {"media": "http://pics.dmm.co.jp/digital/video/beb00037/beb00037pl.jpg"}, "text": "for Fun"}, {"headline": "BEB038", "startDate": 38, "endDate": 38, "asset": {"media": "http://pics.dmm.co.jp/digital/video/beb00038/beb00038pl.jpg"}, "text": "for Fun"}, {"headline": "BEB039", "startDate": 39, "endDate": 39, "asset": {"media": "http://pics.dmm.co.jp/digital/video/beb00039/beb00039pl.jpg"}, "text": "for Fun"}, {"headline": "BEB040", "startDate": 40, "endDate": 40, "asset": {"media": "http://pics.dmm.co.jp/digital/video/beb00040/beb00040pl.jpg"}, "text": "for Fun"}, {"headline": "BEB041", "startDate": 41, "endDate": 41, "asset": {"media": "http://pics.dmm.co.jp/digital/video/beb00041/beb00041pl.jpg"}, "text": "for Fun"}, {"headline": "BEB042", "startDate": 42, "endDate": 42, "asset": {"media": "http://pics.dmm.co.jp/digital/video/beb00042/beb00042pl.jpg"}, "text": "for Fun"}, {"headline": "BEB043", "startDate": 43, "endDate": 43, "asset": {"media": "http://pics.dmm.co.jp/digital/video/beb00043/beb00043pl.jpg"}, "text": "for Fun"}, {"headline": "BEB044", "startDate": 44, "endDate": 44, "asset": {"media": "http://pics.dmm.co.jp/digital/video/beb00044/beb00044pl.jpg"}, "text": "for Fun"}, {"headline": "BEB045", "startDate": 45, "endDate": 45, "asset": {"media": "http://pics.dmm.co.jp/digital/video/beb00045/beb00045pl.jpg"}, "text": "for Fun"}, {"headline": "BEB046", "startDate": 46, "endDate": 46, "asset": {"media": "http://pics.dmm.co.jp/digital/video/beb00046/beb00046pl.jpg"}, "text": "for Fun"}, {"headline": "BEB047", "startDate": 47, "endDate": 47, "asset": {"media": "http://pics.dmm.co.jp/digital/video/beb00047/beb00047pl.jpg"}, "text": "for Fun"}, {"headline": "BEB048", "startDate": 48, "endDate": 48, "asset": {"media": "http://pics.dmm.co.jp/digital/video/beb00048/beb00048pl.jpg"}, "text": "for Fun"}, {"headline": "BEB049", "startDate": 49, "endDate": 49, "asset": {"media": "http://pics.dmm.co.jp/digital/video/beb00049/beb00049pl.jpg"}, "text": "for Fun"}, {"headline": "BEB050", "startDate": 50, "endDate": 50, "asset": {"media": "http://pics.dmm.co.jp/digital/video/beb00050/beb00050pl.jpg"}, "text": "for Fun"}, {"headline": "BEB051", "startDate": 51, "endDate": 51, "asset": {"media": "http://pics.dmm.co.jp/digital/video/beb00051/beb00051pl.jpg"}, "text": "for Fun"}, {"headline": "BEB052", "startDate": 52, "endDate": 52, "asset": {"media": "http://pics.dmm.co.jp/digital/video/beb00052/beb00052pl.jpg"}, "text": "for Fun"}, {"headline": "BEB053", "startDate": 53, "endDate": 53, "asset": {"media": "http://pics.dmm.co.jp/digital/video/beb00053/beb00053pl.jpg"}, "text": "for Fun"}, {"headline": "BEB054", "startDate": 54, "endDate": 54, "asset": {"media": "http://pics.dmm.co.jp/digital/video/beb00054/beb00054pl.jpg"}, "text": "for Fun"}, {"headline": "BEB055", "startDate": 55, "endDate": 55, "asset": {"media": "http://pics.dmm.co.jp/digital/video/beb00055/beb00055pl.jpg"}, "text": "for Fun"}, {"headline": "BEB056", "startDate": 56, "endDate": 56, "asset": {"media": "http://pics.dmm.co.jp/digital/video/beb00056/beb00056pl.jpg"}, "text": "for Fun"}, {"headline": "BEB057", "startDate": 57, "endDate": 57, "asset": {"media": "http://pics.dmm.co.jp/digital/video/beb00057/beb00057pl.jpg"}, "text": "for Fun"}, {"headline": "BEB058", "startDate": 58, "endDate": 58, "asset": {"media": "http://pics.dmm.co.jp/digital/video/beb00058/beb00058pl.jpg"}, "text": "for Fun"}, {"headline": "BEB059", "startDate": 59, "endDate": 59, "asset": {"media": "http://pics.dmm.co.jp/digital/video/beb00059/beb00059pl.jpg"}, "text": "for Fun"}, {"headline": "BEB060", "startDate": 60, "endDate": 60, "asset": {"media": "http://pics.dmm.co.jp/digital/video/beb00060/beb00060pl.jpg"}, "text": "for Fun"}, {"headline": "BEB061", "startDate": 61, "endDate": 61, "asset": {"media": "http://pics.dmm.co.jp/digital/video/beb00061/beb00061pl.jpg"}, "text": "for Fun"}, {"headline": "BEB062", "startDate": 62, "endDate": 62, "asset": {"media": "http://pics.dmm.co.jp/digital/video/beb00062/beb00062pl.jpg"}, "text": "for Fun"}, {"headline": "BEB063", "startDate": 63, "endDate": 63, "asset": {"media": "http://pics.dmm.co.jp/digital/video/beb00063/beb00063pl.jpg"}, "text": "for Fun"}, {"headline": "BEB064", "startDate": 64, "endDate": 64, "asset": {"media": "http://pics.dmm.co.jp/digital/video/beb00064/beb00064pl.jpg"}, "text": "for Fun"}, {"headline": "BEB065", "startDate": 65, "endDate": 65, "asset": {"media": "http://pics.dmm.co.jp/digital/video/beb00065/beb00065pl.jpg"}, "text": "for Fun"}, {"headline": "BEB066", "startDate": 66, "endDate": 66, "asset": {"media": "http://pics.dmm.co.jp/digital/video/beb00066/beb00066pl.jpg"}, "text": "for Fun"}, {"headline": "BEB067", "startDate": 67, "endDate": 67, "asset": {"media": "http://pics.dmm.co.jp/digital/video/beb00067/beb00067pl.jpg"}, "text": "for Fun"}, {"headline": "BEB068", "startDate": 68, "endDate": 68, "asset": {"media": "http://pics.dmm.co.jp/digital/video/beb00068/beb00068pl.jpg"}, "text": "for Fun"}, {"headline": "BEB069", "startDate": 69, "endDate": 69, "asset": {"media": "http://pics.dmm.co.jp/digital/video/beb00069/beb00069pl.jpg"}, "text": "for Fun"}, {"headline": "BEB070", "startDate": 70, "endDate": 70, "asset": {"media": "http://pics.dmm.co.jp/digital/video/beb00070/beb00070pl.jpg"}, "text": "for Fun"}, {"headline": "BEB071", "startDate": 71, "endDate": 71, "asset": {"media": "http://pics.dmm.co.jp/digital/video/beb00071/beb00071pl.jpg"}, "text": "for Fun"}, {"headline": "BEB072", "startDate": 72, "endDate": 72, "asset": {"media": "http://pics.dmm.co.jp/digital/video/beb00072/beb00072pl.jpg"}, "text": "for Fun"}, {"headline": "BEB073", "startDate": 73, "endDate": 73, "asset": {"media": "http://pics.dmm.co.jp/digital/video/beb00073/beb00073pl.jpg"}, "text": "for Fun"}, {"headline": "BEB074", "startDate": 74, "endDate": 74, "asset": {"media": "http://pics.dmm.co.jp/digital/video/beb00074/beb00074pl.jpg"}, "text": "for Fun"}, {"headline": "BEB075", "startDate": 75, "endDate": 75, "asset": {"media": "http://pics.dmm.co.jp/digital/video/beb00075/beb00075pl.jpg"}, "text": "for Fun"}, {"headline": "BEB076", "startDate": 76, "endDate": 76, "asset": {"media": "http://pics.dmm.co.jp/digital/video/beb00076/beb00076pl.jpg"}, "text": "for Fun"}, {"headline": "BEB077", "startDate": 77, "endDate": 77, "asset": {"media": "http://pics.dmm.co.jp/digital/video/beb00077/beb00077pl.jpg"}, "text": "for Fun"}, {"headline": "BEB078", "startDate": 78, "endDate": 78, "asset": {"media": "http://pics.dmm.co.jp/digital/video/beb00078/beb00078pl.jpg"}, "text": "for Fun"}, {"headline": "BEB079", "startDate": 79, "endDate": 79, "asset": {"media": "http://pics.dmm.co.jp/digital/video/beb00079/beb00079pl.jpg"}, "text": "for Fun"}, {"headline": "BEB080", "startDate": 80, "endDate": 80, "asset": {"media": "http://pics.dmm.co.jp/digital/video/beb00080/beb00080pl.jpg"}, "text": "for Fun"}, {"headline": "BEB081", "startDate": 81, "endDate": 81, "asset": {"media": "http://pics.dmm.co.jp/digital/video/beb00081/beb00081pl.jpg"}, "text": "for Fun"}, {"headline": "BEB082", "startDate": 82, "endDate": 82, "asset": {"media": "http://pics.dmm.co.jp/digital/video/beb00082/beb00082pl.jpg"}, "text": "for Fun"}, {"headline": "BEB083", "startDate": 83, "endDate": 83, "asset": {"media": "http://pics.dmm.co.jp/digital/video/beb00083/beb00083pl.jpg"}, "text": "for Fun"}, {"headline": "BEB084", "startDate": 84, "endDate": 84, "asset": {"media": "http://pics.dmm.co.jp/digital/video/beb00084/beb00084pl.jpg"}, "text": "for Fun"}, {"headline": "BEB085", "startDate": 85, "endDate": 85, "asset": {"media": "http://pics.dmm.co.jp/digital/video/beb00085/beb00085pl.jpg"}, "text": "for Fun"}, {"headline": "BEB086", "startDate": 86, "endDate": 86, "asset": {"media": "http://pics.dmm.co.jp/digital/video/beb00086/beb00086pl.jpg"}, "text": "for Fun"}, {"headline": "BEB087", "startDate": 87, "endDate": 87, "asset": {"media": "http://pics.dmm.co.jp/digital/video/beb00087/beb00087pl.jpg"}, "text": "for Fun"}, {"headline": "BEB088", "startDate": 88, "endDate": 88, "asset": {"media": "http://pics.dmm.co.jp/digital/video/beb00088/beb00088pl.jpg"}, "text": "for Fun"}, {"headline": "BEB089", "startDate": 89, "endDate": 89, "asset": {"media": "http://pics.dmm.co.jp/digital/video/beb00089/beb00089pl.jpg"}, "text": "for Fun"}, {"headline": "BEB090", "startDate": 90, "endDate": 90, "asset": {"media": "http://pics.dmm.co.jp/digital/video/beb00090/beb00090pl.jpg"}, "text": "for Fun"}, {"headline": "BEB091", "startDate": 91, "endDate": 91, "asset": {"media": "http://pics.dmm.co.jp/digital/video/beb00091/beb00091pl.jpg"}, "text": "for Fun"}, {"headline": "BEB092", "startDate": 92, "endDate": 92, "asset": {"media": "http://pics.dmm.co.jp/digital/video/beb00092/beb00092pl.jpg"}, "text": "for Fun"}, {"headline": "BEB093", "startDate": 93, "endDate": 93, "asset": {"media": "http://pics.dmm.co.jp/digital/video/beb00093/beb00093pl.jpg"}, "text": "for Fun"}, {"headline": "BEB094", "startDate": 94, "endDate": 94, "asset": {"media": "http://pics.dmm.co.jp/digital/video/beb00094/beb00094pl.jpg"}, "text": "for Fun"}, {"headline": "BEB095", "startDate": 95, "endDate": 95, "asset": {"media": "http://pics.dmm.co.jp/digital/video/beb00095/beb00095pl.jpg"}, "text": "for Fun"}, {"headline": "BEB096", "startDate": 96, "endDate": 96, "asset": {"media": "http://pics.dmm.co.jp/digital/video/beb00096/beb00096pl.jpg"}, "text": "for Fun"}, {"headline": "BEB097", "startDate": 97, "endDate": 97, "asset": {"media": "http://pics.dmm.co.jp/digital/video/beb00097/beb00097pl.jpg"}, "text": "for Fun"}, {"headline": "BEB098", "startDate": 98, "endDate": 98, "asset": {"media": "http://pics.dmm.co.jp/digital/video/beb00098/beb00098pl.jpg"}, "text": "for Fun"}, {"headline": "BEB099", "startDate": 99, "endDate": 99, "asset": {"media": "http://pics.dmm.co.jp/digital/video/beb00099/beb00099pl.jpg"}, "text": "for Fun"}, {"headline": "BEB100", "startDate": 100, "endDate": 100, "asset": {"media": "http://pics.dmm.co.jp/digital/video/beb00100/beb00100pl.jpg"}, "text": "for Fun"}, {"headline": "BEB101", "startDate": 101, "endDate": 101, "asset": {"media": "http://pics.dmm.co.jp/digital/video/beb00101/beb00101pl.jpg"}, "text": "for Fun"}, {"headline": "BEB102", "startDate": 102, "endDate": 102, "asset": {"media": "http://pics.dmm.co.jp/digital/video/beb00102/beb00102pl.jpg"}, "text": "for Fun"}, {"headline": "BEB103", "startDate": 103, "endDate": 103, "asset": {"media": "http://pics.dmm.co.jp/digital/video/beb00103/beb00103pl.jpg"}, "text": "for Fun"}, {"headline": "BEB104", "startDate": 104, "endDate": 104, "asset": {"media": "http://pics.dmm.co.jp/digital/video/beb00104/beb00104pl.jpg"}, "text": "for Fun"}, {"headline": "BEB105", "startDate": 105, "endDate": 105, "asset": {"media": "http://pics.dmm.co.jp/digital/video/beb00105/beb00105pl.jpg"}, "text": "for Fun"}, {"headline": "BEB106", "startDate": 106, "endDate": 106, "asset": {"media": "http://pics.dmm.co.jp/digital/video/beb00106/beb00106pl.jpg"}, "text": "for Fun"}, {"headline": "BEB107", "startDate": 107, "endDate": 107, "asset": {"media": "http://pics.dmm.co.jp/digital/video/beb00107/beb00107pl.jpg"}, "text": "for Fun"}, {"headline": "BEB108", "startDate": 108, "endDate": 108, "asset": {"media": "http://pics.dmm.co.jp/digital/video/beb00108/beb00108pl.jpg"}, "text": "for Fun"}, {"headline": "BEB109", "startDate": 109, "endDate": 109, "asset": {"media": "http://pics.dmm.co.jp/digital/video/beb00109/beb00109pl.jpg"}, "text": "for Fun"}, {"headline": "BEB110", "startDate": 110, "endDate": 110, "asset": {"media": "http://pics.dmm.co.jp/digital/video/beb00110/beb00110pl.jpg"}, "text": "for Fun"}, {"headline": "BEB111", "startDate": 111, "endDate": 111, "asset": {"media": "http://pics.dmm.co.jp/digital/video/beb00111/beb00111pl.jpg"}, "text": "for Fun"}, {"headline": "BEB112", "startDate": 112, "endDate": 112, "asset": {"media": "http://pics.dmm.co.jp/digital/video/beb00112/beb00112pl.jpg"}, "text": "for Fun"}, {"headline": "BEB113", "startDate": 113, "endDate": 113, "asset": {"media": "http://pics.dmm.co.jp/digital/video/beb00113/beb00113pl.jpg"}, "text": "for Fun"}, {"headline": "BEB114", "startDate": 114, "endDate": 114, "asset": {"media": "http://pics.dmm.co.jp/digital/video/beb00114/beb00114pl.jpg"}, "text": "for Fun"}, {"headline": "BEB115", "startDate": 115, "endDate": 115, "asset": {"media": "http://pics.dmm.co.jp/digital/video/beb00115/beb00115pl.jpg"}, "text": "for Fun"}, {"headline": "BEB116", "startDate": 116, "endDate": 116, "asset": {"media": "http://pics.dmm.co.jp/digital/video/beb00116/beb00116pl.jpg"}, "text": "for Fun"}, {"headline": "BEB117", "startDate": 117, "endDate": 117, "asset": {"media": "http://pics.dmm.co.jp/digital/video/beb00117/beb00117pl.jpg"}, "text": "for Fun"}, {"headline": "BEB118", "startDate": 118, "endDate": 118, "asset": {"media": "http://pics.dmm.co.jp/digital/video/beb00118/beb00118pl.jpg"}, "text": "for Fun"}, {"headline": "BEB119", "startDate": 119, "endDate": 119, "asset": {"media": "http://pics.dmm.co.jp/digital/video/beb00119/beb00119pl.jpg"}, "text": "for Fun"}, {"headline": "BEB120", "startDate": 120, "endDate": 120, "asset": {"media": "http://pics.dmm.co.jp/digital/video/beb00120/beb00120pl.jpg"}, "text": "for Fun"}, {"headline": "BEB121", "startDate": 121, "endDate": 121, "asset": {"media": "http://pics.dmm.co.jp/digital/video/beb00121/beb00121pl.jpg"}, "text": "for Fun"}, {"headline": "BEB122", "startDate": 122, "endDate": 122, "asset": {"media": "http://pics.dmm.co.jp/digital/video/beb00122/beb00122pl.jpg"}, "text": "for Fun"}, {"headline": "BEB123", "startDate": 123, "endDate": 123, "asset": {"media": "http://pics.dmm.co.jp/digital/video/beb00123/beb00123pl.jpg"}, "text": "for Fun"}, {"headline": "BEB124", "startDate": 124, "endDate": 124, "asset": {"media": "http://pics.dmm.co.jp/digital/video/beb00124/beb00124pl.jpg"}, "text": "for Fun"}, {"headline": "BEB125", "startDate": 125, "endDate": 125, "asset": {"media": "http://pics.dmm.co.jp/digital/video/beb00125/beb00125pl.jpg"}, "text": "for Fun"}, {"headline": "BEB126", "startDate": 126, "endDate": 126, "asset": {"media": "http://pics.dmm.co.jp/digital/video/beb00126/beb00126pl.jpg"}, "text": "for Fun"}, {"headline": "BEB127", "startDate": 127, "endDate": 127, "asset": {"media": "http://pics.dmm.co.jp/digital/video/beb00127/beb00127pl.jpg"}, "text": "for Fun"}, {"headline": "BEB128", "startDate": 128, "endDate": 128, "asset": {"media": "http://pics.dmm.co.jp/digital/video/beb00128/beb00128pl.jpg"}, "text": "for Fun"}, {"headline": "BEB129", "startDate": 129, "endDate": 129, "asset": {"media": "http://pics.dmm.co.jp/digital/video/beb00129/beb00129pl.jpg"}, "text": "for Fun"}, {"headline": "BEB130", "startDate": 130, "endDate": 130, "asset": {"media": "http://pics.dmm.co.jp/digital/video/beb00130/beb00130pl.jpg"}, "text": "for Fun"}, {"headline": "BEB131", "startDate": 131, "endDate": 131, "asset": {"media": "http://pics.dmm.co.jp/digital/video/beb00131/beb00131pl.jpg"}, "text": "for Fun"}, {"headline": "BEB132", "startDate": 132, "endDate": 132, "asset": {"media": "http://pics.dmm.co.jp/digital/video/beb00132/beb00132pl.jpg"}, "text": "for Fun"}, {"headline": "BEB133", "startDate": 133, "endDate": 133, "asset": {"media": "http://pics.dmm.co.jp/digital/video/beb00133/beb00133pl.jpg"}, "text": "for Fun"}, {"headline": "BEB134", "startDate": 134, "endDate": 134, "asset": {"media": "http://pics.dmm.co.jp/digital/video/beb00134/beb00134pl.jpg"}, "text": "for Fun"}, {"headline": "BEB135", "startDate": 135, "endDate": 135, "asset": {"media": "http://pics.dmm.co.jp/digital/video/beb00135/beb00135pl.jpg"}, "text": "for Fun"}, {"headline": "BEB136", "startDate": 136, "endDate": 136, "asset": {"media": "http://pics.dmm.co.jp/digital/video/beb00136/beb00136pl.jpg"}, "text": "for Fun"}, {"headline": "BEB137", "startDate": 137, "endDate": 137, "asset": {"media": "http://pics.dmm.co.jp/digital/video/beb00137/beb00137pl.jpg"}, "text": "for Fun"}, {"headline": "BEB138", "startDate": 138, "endDate": 138, "asset": {"media": "http://pics.dmm.co.jp/digital/video/beb00138/beb00138pl.jpg"}, "text": "for Fun"}, {"headline": "BEB139", "startDate": 139, "endDate": 139, "asset": {"media": "http://pics.dmm.co.jp/digital/video/beb00139/beb00139pl.jpg"}, "text": "for Fun"}, {"headline": "BEB140", "startDate": 140, "endDate": 140, "asset": {"media": "http://pics.dmm.co.jp/digital/video/beb00140/beb00140pl.jpg"}, "text": "for Fun"}, {"headline": "BEB141", "startDate": 141, "endDate": 141, "asset": {"media": "http://pics.dmm.co.jp/digital/video/beb00141/beb00141pl.jpg"}, "text": "for Fun"}, {"headline": "BEB142", "startDate": 142, "endDate": 142, "asset": {"media": "http://pics.dmm.co.jp/digital/video/beb00142/beb00142pl.jpg"}, "text": "for Fun"}, {"headline": "BEB143", "startDate": 143, "endDate": 143, "asset": {"media": "http://pics.dmm.co.jp/digital/video/beb00143/beb00143pl.jpg"}, "text": "for Fun"}, {"headline": "BEB144", "startDate": 144, "endDate": 144, "asset": {"media": "http://pics.dmm.co.jp/digital/video/beb00144/beb00144pl.jpg"}, "text": "for Fun"}, {"headline": "BEB145", "startDate": 145, "endDate": 145, "asset": {"media": "http://pics.dmm.co.jp/digital/video/beb00145/beb00145pl.jpg"}, "text": "for Fun"}, {"headline": "BEB146", "startDate": 146, "endDate": 146, "asset": {"media": "http://pics.dmm.co.jp/digital/video/beb00146/beb00146pl.jpg"}, "text": "for Fun"}, {"headline": "BEB147", "startDate": 147, "endDate": 147, "asset": {"media": "http://pics.dmm.co.jp/digital/video/beb00147/beb00147pl.jpg"}, "text": "for Fun"}, {"headline": "BEB148", "startDate": 148, "endDate": 148, "asset": {"media": "http://pics.dmm.co.jp/digital/video/beb00148/beb00148pl.jpg"}, "text": "for Fun"}, {"headline": "BEB149", "startDate": 149, "endDate": 149, "asset": {"media": "http://pics.dmm.co.jp/digital/video/beb00149/beb00149pl.jpg"}, "text": "for Fun"}, {"headline": "BEB150", "startDate": 150, "endDate": 150, "asset": {"media": "http://pics.dmm.co.jp/digital/video/beb00150/beb00150pl.jpg"}, "text": "for Fun"}], "startDate": "0"}}